[
  {
    "op": "replace",
    "path": "/data/VAULTHOST",
    "value": "https://vault-spi-vault.apps.0e2d3437593ef846e766.hypershift.aws-2.ci.openshift.org"
  },
  {
    "op": "replace",
    "path": "/data/BASEURL",
    "value": "https://spi-oauth-spi-system.apps.0e2d3437593ef846e766.hypershift.aws-2.ci.openshift.org"
  },
  {
    "op": "add",
    "path": "/data/INSTANCEID",
    "value": "spi-dev"
  },
  {
    "op": "add",
    "path": "/data/VAULTINSECURETLS",
    "value": "true"
  },
  {
    "op": "add",
    "path": "/data/TOKENSTORAGE",
    "value": "vault"
  }
]
